autohooks/plugins/flake8/__init__.py
autohooks/plugins/flake8/__version__.py
autohooks/plugins/flake8/flake8.py
autohooks_plugin_flake8-23.10.0.dist-info/LICENSE
autohooks_plugin_flake8-23.10.0.dist-info/METADATA
autohooks_plugin_flake8-23.10.0.dist-info/WHEEL
autohooks_plugin_flake8-23.10.0.dist-info/RECORD
