Metadata-Version: 2.1
Name: autohooks-plugin-flake8
Version: 23.10.0
Summary: An autohooks plugin for python code linting via flake8.
Home-page: https://github.com/greenbone/autohooks-plugin-flake8
License: GPL-3.0-or-later
Keywords: git,linting,hooks,flake8
Author: Greenbone AG
Author-email: info@greenbone.net
Requires-Python: >=3.9,<4.0
Classifier: Development Status :: 5 - Production/Stable
Classifier: Environment :: Console
Classifier: Intended Audience :: Developers
Classifier: Intended Audience :: System Administrators
Classifier: License :: OSI Approved :: GNU General Public License v3 or later (GPLv3+)
Classifier: Operating System :: OS Independent
Classifier: Programming Language :: Python :: 3
Classifier: Programming Language :: Python :: 3.9
Classifier: Programming Language :: Python :: 3.10
Classifier: Programming Language :: Python :: 3.11
Classifier: Programming Language :: Python :: 3.12
Classifier: Topic :: Software Development :: Libraries :: Python Modules
Classifier: Topic :: Software Development :: Version Control :: Git
Requires-Dist: autohooks (>=21.3.0)
Requires-Dist: flake8 (>=5.0.4)
Project-URL: Repository, https://github.com/greenbone/autohooks-plugin-flake8
